<?xml version="1.0" encoding="UTF-8" standalone="no"?><location BACKGROUND="bus_stop" BOOLMAP="bus_stop" FOREGROUND="bus_stop_f" LOCID="bus_stop"><backgroundSound volume="0.5">arctic_wind</backgroundSound><stuffs><screwdriver height="17" width="7" x="105" y="142"><bitmap scale="0.5" x="95" y="143">screwdriver</bitmap><pickup/><toCome x="108" y="171"/></screwdriver></stuffs><arrows><toCottageFront height="180" imageX="288" imageY="96" location="cottage_front" width="36" x="284" y="0"><pos>RIGHT</pos><size>SMALL</size><toCome x="343" y="169"/><toFinal right="true" x="31" y="176"/></toCottageFront></arrows></location>